LICENSE
README.md
requirements.txt
setup.py
filecrawler/__init__.py
filecrawler/__main__.py
filecrawler/__meta__.py
filecrawler/_exceptions.py
filecrawler/alertbase.py
filecrawler/args.py
filecrawler/config.py
filecrawler/crawlerbase.py
filecrawler/filecrawler.py
filecrawler/gitfinder.py
filecrawler/parserbase.py
filecrawler/password.py
filecrawler/rulebase.py
filecrawler.egg-info/PKG-INFO
filecrawler.egg-info/SOURCES.txt
filecrawler.egg-info/dependency_links.txt
filecrawler.egg-info/entry_points.txt
filecrawler.egg-info/not-zip-safe
filecrawler.egg-info/requires.txt
filecrawler.egg-info/top_level.txt
filecrawler/alerts/__init__.py
filecrawler/alerts/telegram.py
filecrawler/cmd/__init__.py
filecrawler/cmd/elastic.py
filecrawler/cmd/local.py
filecrawler/libs/__init__.py
filecrawler/libs/alert.py
filecrawler/libs/color.py
filecrawler/libs/containerfile.py
filecrawler/libs/cpath.py
filecrawler/libs/crawlerdb.py
filecrawler/libs/database.py
filecrawler/libs/file.py
filecrawler/libs/logger.py
filecrawler/libs/module.py
filecrawler/libs/parser.py
filecrawler/libs/process.py
filecrawler/libs/rule.py
filecrawler/libs/slice.py
filecrawler/libs/worker.py
filecrawler/libs/bin/__init__.py
filecrawler/libs/bin/jadx.sh
filecrawler/libs/bin/loader.pdf
filecrawler/libs/libmagic_windows/README.md
filecrawler/libs/libmagic_windows/__init__.py
filecrawler/libs/libmagic_windows/libgnurx-0.dll
filecrawler/libs/libmagic_windows/magic.mgc
filecrawler/libs/libmagic_windows/magic1.dll
filecrawler/parsers/__init__.py
filecrawler/parsers/certparser.py
filecrawler/parsers/default.py
filecrawler/parsers/imageparser.py
filecrawler/parsers/intelxinfo.py
filecrawler/parsers/javaparser.py
filecrawler/parsers/jsonparser.py
filecrawler/parsers/officeparser.py
filecrawler/parsers/pcapparser.py
filecrawler/parsers/pdfparser.py
filecrawler/parsers/sqliteparser.py
filecrawler/parsers/vdiskparser.py
filecrawler/parsers/windowsbinparser.py
filecrawler/parsers/xmlparser.py
filecrawler/parsers/yamlparser.py
filecrawler/rules/__init__.py
filecrawler/rules/adafruit.py
filecrawler/rules/adobe.py
filecrawler/rules/age.py
filecrawler/rules/aws.py
filecrawler/rules/azure.py
filecrawler/rules/github.py
filecrawler/rules/gitlab.py
